sankalp/__init__.py
sankalp/__main__.py
sankalp/blue.mp3
sankalp/cli.py
sankalp-1.3.6.dist-info/METADATA
sankalp-1.3.6.dist-info/WHEEL
sankalp-1.3.6.dist-info/entry_points.txt
sankalp-1.3.6.dist-info/top_level.txt
sankalp-1.3.6.dist-info/RECORD
