Metadata-Version: 2.4
Name: sankalp
Version: 1.3.6
Summary: A CLI package for Sankalp Shrivastava
Home-page: https://github.com/1sankalp
Author: Sankalp Shrivastava
Author-email: 1sankalpshrivastava@gmail.com
Requires-Python: >=3.6
Requires-Dist: rich
Requires-Dist: PyInquirer
Requires-Dist: pygame
Requires-Dist: windows-curses; platform_system == "Windows"
Dynamic: author
Dynamic: author-email
Dynamic: description
Dynamic: description-content-type
Dynamic: home-page
Dynamic: requires-dist
Dynamic: requires-python
Dynamic: summary
